{"nodes": [{"id": "c_users_vitou_laravel13_x_examples_basic_laravel_filamentphp_vendor_league_csv_src_rfc4180field_php", "label": "RFC4180Field.php", "file_type": "code", "source_file": "C:\\Users\\vitou\\laravel13.x\\examples\\basic-laravel-filamentphp\\vendor\\league\\csv\\src\\RFC4180Field.php", "source_location": "L1"}, {"id": "rfc4180field_rfc4180field", "label": "RFC4180Field", "file_type": "code", "source_file": "C:\\Users\\vitou\\laravel13.x\\examples\\basic-laravel-filamentphp\\vendor\\league\\csv\\src\\RFC4180Field.php", "source_location": "L51"}, {"id": "rfc4180field_rfc4180field_addto", "label": ".addTo()", "file_type": "code", "source_file": "C:\\Users\\vitou\\laravel13.x\\examples\\basic-laravel-filamentphp\\vendor\\league\\csv\\src\\RFC4180Field.php", "source_location": "L78"}, {"id": "rfc4180field_rfc4180field_addformatterto", "label": ".addFormatterTo()", "file_type": "code", "source_file": "C:\\Users\\vitou\\laravel13.x\\examples\\basic-laravel-filamentphp\\vendor\\league\\csv\\src\\RFC4180Field.php", "source_location": "L100"}, {"id": "rfc4180field_rfc4180field_register", "label": ".register()", "file_type": "code", "source_file": "C:\\Users\\vitou\\laravel13.x\\examples\\basic-laravel-filamentphp\\vendor\\league\\csv\\src\\RFC4180Field.php", "source_location": "L117"}, {"id": "rfc4180field_rfc4180field_getfiltername", "label": ".getFiltername()", "file_type": "code", "source_file": "C:\\Users\\vitou\\laravel13.x\\examples\\basic-laravel-filamentphp\\vendor\\league\\csv\\src\\RFC4180Field.php", "source_location": "L127"}, {"id": "rfc4180field_rfc4180field_filter", "label": ".filter()", "file_type": "code", "source_file": "C:\\Users\\vitou\\laravel13.x\\examples\\basic-laravel-filamentphp\\vendor\\league\\csv\\src\\RFC4180Field.php", "source_location": "L137"}, {"id": "rfc4180field_rfc4180field_oncreate", "label": ".onCreate()", "file_type": "code", "source_file": "C:\\Users\\vitou\\laravel13.x\\examples\\basic-laravel-filamentphp\\vendor\\league\\csv\\src\\RFC4180Field.php", "source_location": "L160"}, {"id": "rfc4180field_rfc4180field_isvalidparams", "label": ".isValidParams()", "file_type": "code", "source_file": "C:\\Users\\vitou\\laravel13.x\\examples\\basic-laravel-filamentphp\\vendor\\league\\csv\\src\\RFC4180Field.php", "source_location": "L197"}, {"id": "rfc4180field_rfc4180field_isvalidsequence", "label": ".isValidSequence()", "file_type": "code", "source_file": "C:\\Users\\vitou\\laravel13.x\\examples\\basic-laravel-filamentphp\\vendor\\league\\csv\\src\\RFC4180Field.php", "source_location": "L209"}], "edges": [{"source": "c_users_vitou_laravel13_x_examples_basic_laravel_filamentphp_vendor_league_csv_src_rfc4180field_php", "target": "deprecated", "relation": "imports", "confidence": "EXTRACTED", "source_file": "C:\\Users\\vitou\\laravel13.x\\examples\\basic-laravel-filamentphp\\vendor\\league\\csv\\src\\RFC4180Field.php", "source_location": "L16", "weight": 1.0}, {"source": "c_users_vitou_laravel13_x_examples_basic_laravel_filamentphp_vendor_league_csv_src_rfc4180field_php", "target": "invalidargumentexception", "relation": "imports", "confidence": "EXTRACTED", "source_file": "C:\\Users\\vitou\\laravel13.x\\examples\\basic-laravel-filamentphp\\vendor\\league\\csv\\src\\RFC4180Field.php", "source_location": "L17", "weight": 1.0}, {"source": "c_users_vitou_laravel13_x_examples_basic_laravel_filamentphp_vendor_league_csv_src_rfc4180field_php", "target": "php_user_filter", "relation": "imports", "confidence": "EXTRACTED", "source_file": "C:\\Users\\vitou\\laravel13.x\\examples\\basic-laravel-filamentphp\\vendor\\league\\csv\\src\\RFC4180Field.php", "source_location": "L18", "weight": 1.0}, {"source": "c_users_vitou_laravel13_x_examples_basic_laravel_filamentphp_vendor_league_csv_src_rfc4180field_php", "target": "throwable", "relation": "imports", "confidence": "EXTRACTED", "source_file": "C:\\Users\\vitou\\laravel13.x\\examples\\basic-laravel-filamentphp\\vendor\\league\\csv\\src\\RFC4180Field.php", "source_location": "L19", "weight": 1.0}, {"source": "c_users_vitou_laravel13_x_examples_basic_laravel_filamentphp_vendor_league_csv_src_rfc4180field_php", "target": "typeerror", "relation": "imports", "confidence": "EXTRACTED", "source_file": "C:\\Users\\vitou\\laravel13.x\\examples\\basic-laravel-filamentphp\\vendor\\league\\csv\\src\\RFC4180Field.php", "source_location": "L20", "weight": 1.0}, {"source": "c_users_vitou_laravel13_x_examples_basic_laravel_filamentphp_vendor_league_csv_src_rfc4180field_php", "target": "array_map", "relation": "imports", "confidence": "EXTRACTED", "source_file": "C:\\Users\\vitou\\laravel13.x\\examples\\basic-laravel-filamentphp\\vendor\\league\\csv\\src\\RFC4180Field.php", "source_location": "L22", "weight": 1.0}, {"source": "c_users_vitou_laravel13_x_examples_basic_laravel_filamentphp_vendor_league_csv_src_rfc4180field_php", "target": "in_array", "relation": "imports", "confidence": "EXTRACTED", "source_file": "C:\\Users\\vitou\\laravel13.x\\examples\\basic-laravel-filamentphp\\vendor\\league\\csv\\src\\RFC4180Field.php", "source_location": "L23", "weight": 1.0}, {"source": "c_users_vitou_laravel13_x_examples_basic_laravel_filamentphp_vendor_league_csv_src_rfc4180field_php", "target": "is_string", "relation": "imports", "confidence": "EXTRACTED", "source_file": "C:\\Users\\vitou\\laravel13.x\\examples\\basic-laravel-filamentphp\\vendor\\league\\csv\\src\\RFC4180Field.php", "source_location": "L24", "weight": 1.0}, {"source": "c_users_vitou_laravel13_x_examples_basic_laravel_filamentphp_vendor_league_csv_src_rfc4180field_php", "target": "str_replace", "relation": "imports", "confidence": "EXTRACTED", "source_file": "C:\\Users\\vitou\\laravel13.x\\examples\\basic-laravel-filamentphp\\vendor\\league\\csv\\src\\RFC4180Field.php", "source_location": "L25", "weight": 1.0}, {"source": "c_users_vitou_laravel13_x_examples_basic_laravel_filamentphp_vendor_league_csv_src_rfc4180field_php", "target": "strcspn", "relation": "imports", "confidence": "EXTRACTED", "source_file": "C:\\Users\\vitou\\laravel13.x\\examples\\basic-laravel-filamentphp\\vendor\\league\\csv\\src\\RFC4180Field.php", "source_location": "L26", "weight": 1.0}, {"source": "c_users_vitou_laravel13_x_examples_basic_laravel_filamentphp_vendor_league_csv_src_rfc4180field_php", "target": "stream_bucket_append", "relation": "imports", "confidence": "EXTRACTED", "source_file": "C:\\Users\\vitou\\laravel13.x\\examples\\basic-laravel-filamentphp\\vendor\\league\\csv\\src\\RFC4180Field.php", "source_location": "L27", "weight": 1.0}, {"source": "c_users_vitou_laravel13_x_examples_basic_laravel_filamentphp_vendor_league_csv_src_rfc4180field_php", "target": "stream_bucket_make_writeable", "relation": "imports", "confidence": "EXTRACTED", "source_file": "C:\\Users\\vitou\\laravel13.x\\examples\\basic-laravel-filamentphp\\vendor\\league\\csv\\src\\RFC4180Field.php", "source_location": "L28", "weight": 1.0}, {"source": "c_users_vitou_laravel13_x_examples_basic_laravel_filamentphp_vendor_league_csv_src_rfc4180field_php", "target": "stream_bucket_new", "relation": "imports", "confidence": "EXTRACTED", "source_file": "C:\\Users\\vitou\\laravel13.x\\examples\\basic-laravel-filamentphp\\vendor\\league\\csv\\src\\RFC4180Field.php", "source_location": "L29", "weight": 1.0}, {"source": "c_users_vitou_laravel13_x_examples_basic_laravel_filamentphp_vendor_league_csv_src_rfc4180field_php", "target": "stream_filter_register", "relation": "imports", "confidence": "EXTRACTED", "source_file": "C:\\Users\\vitou\\laravel13.x\\examples\\basic-laravel-filamentphp\\vendor\\league\\csv\\src\\RFC4180Field.php", "source_location": "L30", "weight": 1.0}, {"source": "c_users_vitou_laravel13_x_examples_basic_laravel_filamentphp_vendor_league_csv_src_rfc4180field_php", "target": "stream_get_filters", "relation": "imports", "confidence": "EXTRACTED", "source_file": "C:\\Users\\vitou\\laravel13.x\\examples\\basic-laravel-filamentphp\\vendor\\league\\csv\\src\\RFC4180Field.php", "source_location": "L31", "weight": 1.0}, {"source": "c_users_vitou_laravel13_x_examples_basic_laravel_filamentphp_vendor_league_csv_src_rfc4180field_php", "target": "strlen", "relation": "imports", "confidence": "EXTRACTED", "source_file": "C:\\Users\\vitou\\laravel13.x\\examples\\basic-laravel-filamentphp\\vendor\\league\\csv\\src\\RFC4180Field.php", "source_location": "L32", "weight": 1.0}, {"source": "c_users_vitou_laravel13_x_examples_basic_laravel_filamentphp_vendor_league_csv_src_rfc4180field_php", "target": "trigger_error", "relation": "imports", "confidence": "EXTRACTED", "source_file": "C:\\Users\\vitou\\laravel13.x\\examples\\basic-laravel-filamentphp\\vendor\\league\\csv\\src\\RFC4180Field.php", "source_location": "L33", "weight": 1.0}, {"source": "c_users_vitou_laravel13_x_examples_basic_laravel_filamentphp_vendor_league_csv_src_rfc4180field_php", "target": "e_user_warning", "relation": "imports", "confidence": "EXTRACTED", "source_file": "C:\\Users\\vitou\\laravel13.x\\examples\\basic-laravel-filamentphp\\vendor\\league\\csv\\src\\RFC4180Field.php", "source_location": "L35", "weight": 1.0}, {"source": "c_users_vitou_laravel13_x_examples_basic_laravel_filamentphp_vendor_league_csv_src_rfc4180field_php", "target": "psfs_err_fatal", "relation": "imports", "confidence": "EXTRACTED", "source_file": "C:\\Users\\vitou\\laravel13.x\\examples\\basic-laravel-filamentphp\\vendor\\league\\csv\\src\\RFC4180Field.php", "source_location": "L36", "weight": 1.0}, {"source": "c_users_vitou_laravel13_x_examples_basic_laravel_filamentphp_vendor_league_csv_src_rfc4180field_php", "target": "psfs_pass_on", "relation": "imports", "confidence": "EXTRACTED", "source_file": "C:\\Users\\vitou\\laravel13.x\\examples\\basic-laravel-filamentphp\\vendor\\league\\csv\\src\\RFC4180Field.php", "source_location": "L37", "weight": 1.0}, {"source": "c_users_vitou_laravel13_x_examples_basic_laravel_filamentphp_vendor_league_csv_src_rfc4180field_php", "target": "stream_filter_read", "relation": "imports", "confidence": "EXTRACTED", "source_file": "C:\\Users\\vitou\\laravel13.x\\examples\\basic-laravel-filamentphp\\vendor\\league\\csv\\src\\RFC4180Field.php", "source_location": "L38", "weight": 1.0}, {"source": "c_users_vitou_laravel13_x_examples_basic_laravel_filamentphp_vendor_league_csv_src_rfc4180field_php", "target": "stream_filter_write", "relation": "imports", "confidence": "EXTRACTED", "source_file": "C:\\Users\\vitou\\laravel13.x\\examples\\basic-laravel-filamentphp\\vendor\\league\\csv\\src\\RFC4180Field.php", "source_location": "L39", "weight": 1.0}, {"source": "c_users_vitou_laravel13_x_examples_basic_laravel_filamentphp_vendor_league_csv_src_rfc4180field_php", "target": "rfc4180field_rfc4180field", "relation": "contains", "confidence": "EXTRACTED", "source_file": "C:\\Users\\vitou\\laravel13.x\\examples\\basic-laravel-filamentphp\\vendor\\league\\csv\\src\\RFC4180Field.php", "source_location": "L51", "weight": 1.0}, {"source": "rfc4180field_rfc4180field", "target": "rfc4180field_rfc4180field_addto", "relation": "method", "confidence": "EXTRACTED", "source_file": "C:\\Users\\vitou\\laravel13.x\\examples\\basic-laravel-filamentphp\\vendor\\league\\csv\\src\\RFC4180Field.php", "source_location": "L78", "weight": 1.0}, {"source": "rfc4180field_rfc4180field", "target": "rfc4180field_rfc4180field_addformatterto", "relation": "method", "confidence": "EXTRACTED", "source_file": "C:\\Users\\vitou\\laravel13.x\\examples\\basic-laravel-filamentphp\\vendor\\league\\csv\\src\\RFC4180Field.php", "source_location": "L100", "weight": 1.0}, {"source": "rfc4180field_rfc4180field", "target": "rfc4180field_rfc4180field_register", "relation": "method", "confidence": "EXTRACTED", "source_file": "C:\\Users\\vitou\\laravel13.x\\examples\\basic-laravel-filamentphp\\vendor\\league\\csv\\src\\RFC4180Field.php", "source_location": "L117", "weight": 1.0}, {"source": "rfc4180field_rfc4180field", "target": "rfc4180field_rfc4180field_getfiltername", "relation": "method", "confidence": "EXTRACTED", "source_file": "C:\\Users\\vitou\\laravel13.x\\examples\\basic-laravel-filamentphp\\vendor\\league\\csv\\src\\RFC4180Field.php", "source_location": "L127", "weight": 1.0}, {"source": "rfc4180field_rfc4180field", "target": "rfc4180field_rfc4180field_filter", "relation": "method", "confidence": "EXTRACTED", "source_file": "C:\\Users\\vitou\\laravel13.x\\examples\\basic-laravel-filamentphp\\vendor\\league\\csv\\src\\RFC4180Field.php", "source_location": "L137", "weight": 1.0}, {"source": "rfc4180field_rfc4180field", "target": "rfc4180field_rfc4180field_oncreate", "relation": "method", "confidence": "EXTRACTED", "source_file": "C:\\Users\\vitou\\laravel13.x\\examples\\basic-laravel-filamentphp\\vendor\\league\\csv\\src\\RFC4180Field.php", "source_location": "L160", "weight": 1.0}, {"source": "rfc4180field_rfc4180field", "target": "rfc4180field_rfc4180field_isvalidparams", "relation": "method", "confidence": "EXTRACTED", "source_file": "C:\\Users\\vitou\\laravel13.x\\examples\\basic-laravel-filamentphp\\vendor\\league\\csv\\src\\RFC4180Field.php", "source_location": "L197", "weight": 1.0}, {"source": "rfc4180field_rfc4180field", "target": "rfc4180field_rfc4180field_isvalidsequence", "relation": "method", "confidence": "EXTRACTED", "source_file": "C:\\Users\\vitou\\laravel13.x\\examples\\basic-laravel-filamentphp\\vendor\\league\\csv\\src\\RFC4180Field.php", "source_location": "L209", "weight": 1.0}, {"source": "rfc4180field_rfc4180field_oncreate", "target": "rfc4180field_rfc4180field_isvalidsequence", "relation": "calls", "confidence": "EXTRACTED", "source_file": "C:\\Users\\vitou\\laravel13.x\\examples\\basic-laravel-filamentphp\\vendor\\league\\csv\\src\\RFC4180Field.php", "source_location": "L185", "weight": 1.0}], "raw_calls": [{"caller_nid": "rfc4180field_rfc4180field_addto", "callee": "self", "source_file": "C:\\Users\\vitou\\laravel13.x\\examples\\basic-laravel-filamentphp\\vendor\\league\\csv\\src\\RFC4180Field.php", "source_location": "L80"}, {"caller_nid": "rfc4180field_rfc4180field_addto", "callee": "getEnclosure", "source_file": "C:\\Users\\vitou\\laravel13.x\\examples\\basic-laravel-filamentphp\\vendor\\league\\csv\\src\\RFC4180Field.php", "source_location": "L83"}, {"caller_nid": "rfc4180field_rfc4180field_addto", "callee": "getEscape", "source_file": "C:\\Users\\vitou\\laravel13.x\\examples\\basic-laravel-filamentphp\\vendor\\league\\csv\\src\\RFC4180Field.php", "source_location": "L84"}, {"caller_nid": "rfc4180field_rfc4180field_addto", "callee": "self", "source_file": "C:\\Users\\vitou\\laravel13.x\\examples\\basic-laravel-filamentphp\\vendor\\league\\csv\\src\\RFC4180Field.php", "source_location": "L89"}, {"caller_nid": "rfc4180field_rfc4180field_addto", "callee": "addStreamFilter", "source_file": "C:\\Users\\vitou\\laravel13.x\\examples\\basic-laravel-filamentphp\\vendor\\league\\csv\\src\\RFC4180Field.php", "source_location": "L93"}, {"caller_nid": "rfc4180field_rfc4180field_addformatterto", "callee": "strlen", "source_file": "C:\\Users\\vitou\\laravel13.x\\examples\\basic-laravel-filamentphp\\vendor\\league\\csv\\src\\RFC4180Field.php", "source_location": "L103"}, {"caller_nid": "rfc4180field_rfc4180field_addformatterto", "callee": "strcspn", "source_file": "C:\\Users\\vitou\\laravel13.x\\examples\\basic-laravel-filamentphp\\vendor\\league\\csv\\src\\RFC4180Field.php", "source_location": "L103"}, {"caller_nid": "rfc4180field_rfc4180field_addformatterto", "callee": "is_string", "source_file": "C:\\Users\\vitou\\laravel13.x\\examples\\basic-laravel-filamentphp\\vendor\\league\\csv\\src\\RFC4180Field.php", "source_location": "L107"}, {"caller_nid": "rfc4180field_rfc4180field_addformatterto", "callee": "str_replace", "source_file": "C:\\Users\\vitou\\laravel13.x\\examples\\basic-laravel-filamentphp\\vendor\\league\\csv\\src\\RFC4180Field.php", "source_location": "L108"}, {"caller_nid": "rfc4180field_rfc4180field_addformatterto", "callee": "addFormatter", "source_file": "C:\\Users\\vitou\\laravel13.x\\examples\\basic-laravel-filamentphp\\vendor\\league\\csv\\src\\RFC4180Field.php", "source_location": "L111"}, {"caller_nid": "rfc4180field_rfc4180field_addformatterto", "callee": "array_map", "source_file": "C:\\Users\\vitou\\laravel13.x\\examples\\basic-laravel-filamentphp\\vendor\\league\\csv\\src\\RFC4180Field.php", "source_location": "L111"}, {"caller_nid": "rfc4180field_rfc4180field_register", "callee": "in_array", "source_file": "C:\\Users\\vitou\\laravel13.x\\examples\\basic-laravel-filamentphp\\vendor\\league\\csv\\src\\RFC4180Field.php", "source_location": "L119"}, {"caller_nid": "rfc4180field_rfc4180field_register", "callee": "stream_get_filters", "source_file": "C:\\Users\\vitou\\laravel13.x\\examples\\basic-laravel-filamentphp\\vendor\\league\\csv\\src\\RFC4180Field.php", "source_location": "L119"}, {"caller_nid": "rfc4180field_rfc4180field_register", "callee": "stream_filter_register", "source_file": "C:\\Users\\vitou\\laravel13.x\\examples\\basic-laravel-filamentphp\\vendor\\league\\csv\\src\\RFC4180Field.php", "source_location": "L120"}, {"caller_nid": "rfc4180field_rfc4180field_filter", "callee": "stream_bucket_make_writeable", "source_file": "C:\\Users\\vitou\\laravel13.x\\examples\\basic-laravel-filamentphp\\vendor\\league\\csv\\src\\RFC4180Field.php", "source_location": "L140"}, {"caller_nid": "rfc4180field_rfc4180field_filter", "callee": "str_replace", "source_file": "C:\\Users\\vitou\\laravel13.x\\examples\\basic-laravel-filamentphp\\vendor\\league\\csv\\src\\RFC4180Field.php", "source_location": "L146"}, {"caller_nid": "rfc4180field_rfc4180field_filter", "callee": "trigger_error", "source_file": "C:\\Users\\vitou\\laravel13.x\\examples\\basic-laravel-filamentphp\\vendor\\league\\csv\\src\\RFC4180Field.php", "source_location": "L148"}, {"caller_nid": "rfc4180field_rfc4180field_filter", "callee": "getMessage", "source_file": "C:\\Users\\vitou\\laravel13.x\\examples\\basic-laravel-filamentphp\\vendor\\league\\csv\\src\\RFC4180Field.php", "source_location": "L148"}, {"caller_nid": "rfc4180field_rfc4180field_filter", "callee": "Warning", "source_file": "C:\\Users\\vitou\\laravel13.x\\examples\\basic-laravel-filamentphp\\vendor\\league\\csv\\src\\RFC4180Field.php", "source_location": "L153"}, {"caller_nid": "rfc4180field_rfc4180field_filter", "callee": "stream_bucket_append", "source_file": "C:\\Users\\vitou\\laravel13.x\\examples\\basic-laravel-filamentphp\\vendor\\league\\csv\\src\\RFC4180Field.php", "source_location": "L154"}, {"caller_nid": "rfc4180field_rfc4180field_filter", "callee": "stream_bucket_new", "source_file": "C:\\Users\\vitou\\laravel13.x\\examples\\basic-laravel-filamentphp\\vendor\\league\\csv\\src\\RFC4180Field.php", "source_location": "L154"}, {"caller_nid": "rfc4180field_rfc4180field_oncreate", "callee": "is_array", "source_file": "C:\\Users\\vitou\\laravel13.x\\examples\\basic-laravel-filamentphp\\vendor\\league\\csv\\src\\RFC4180Field.php", "source_location": "L163"}, {"caller_nid": "rfc4180field_rfc4180field_oncreate", "callee": "isset", "source_file": "C:\\Users\\vitou\\laravel13.x\\examples\\basic-laravel-filamentphp\\vendor\\league\\csv\\src\\RFC4180Field.php", "source_location": "L169"}, {"caller_nid": "rfc4180field_rfc4180field_oncreate", "callee": "strlen", "source_file": "C:\\Users\\vitou\\laravel13.x\\examples\\basic-laravel-filamentphp\\vendor\\league\\csv\\src\\RFC4180Field.php", "source_location": "L170"}, {"caller_nid": "rfc4180field_rfc4180field_oncreate", "callee": "strlen", "source_file": "C:\\Users\\vitou\\laravel13.x\\examples\\basic-laravel-filamentphp\\vendor\\league\\csv\\src\\RFC4180Field.php", "source_location": "L171"}, {"caller_nid": "rfc4180field_rfc4180field_isvalidparams", "callee": "isset", "source_file": "C:\\Users\\vitou\\laravel13.x\\examples\\basic-laravel-filamentphp\\vendor\\league\\csv\\src\\RFC4180Field.php", "source_location": "L201"}, {"caller_nid": "rfc4180field_rfc4180field_isvalidparams", "callee": "strlen", "source_file": "C:\\Users\\vitou\\laravel13.x\\examples\\basic-laravel-filamentphp\\vendor\\league\\csv\\src\\RFC4180Field.php", "source_location": "L202"}, {"caller_nid": "rfc4180field_rfc4180field_isvalidparams", "callee": "strlen", "source_file": "C:\\Users\\vitou\\laravel13.x\\examples\\basic-laravel-filamentphp\\vendor\\league\\csv\\src\\RFC4180Field.php", "source_location": "L203"}, {"caller_nid": "rfc4180field_rfc4180field_isvalidsequence", "callee": "isset", "source_file": "C:\\Users\\vitou\\laravel13.x\\examples\\basic-laravel-filamentphp\\vendor\\league\\csv\\src\\RFC4180Field.php", "source_location": "L211"}, {"caller_nid": "rfc4180field_rfc4180field_isvalidsequence", "callee": "strlen", "source_file": "C:\\Users\\vitou\\laravel13.x\\examples\\basic-laravel-filamentphp\\vendor\\league\\csv\\src\\RFC4180Field.php", "source_location": "L212"}, {"caller_nid": "rfc4180field_rfc4180field_isvalidsequence", "callee": "strcspn", "source_file": "C:\\Users\\vitou\\laravel13.x\\examples\\basic-laravel-filamentphp\\vendor\\league\\csv\\src\\RFC4180Field.php", "source_location": "L212"}]}