{"nodes": [{"id": "c_users_vitou_laravel13_x_examples_basic_laravel_filamentphp_vendor_scrivo_highlight_php_highlight_mode_php", "label": "Mode.php", "file_type": "code", "source_file": "C:\\Users\\vitou\\laravel13.x\\examples\\basic-laravel-filamentphp\\vendor\\scrivo\\highlight.php\\Highlight\\Mode.php", "source_location": "L1"}, {"id": "mode_mode", "label": "Mode", "file_type": "code", "source_file": "C:\\Users\\vitou\\laravel13.x\\examples\\basic-laravel-filamentphp\\vendor\\scrivo\\highlight.php\\Highlight\\Mode.php", "source_location": "L80"}, {"id": "mode_mode_normalize", "label": "._normalize()", "file_type": "code", "source_file": "C:\\Users\\vitou\\laravel13.x\\examples\\basic-laravel-filamentphp\\vendor\\scrivo\\highlight.php\\Highlight\\Mode.php", "source_location": "L93"}, {"id": "mode_mode_handledeprecations", "label": "._handleDeprecations()", "file_type": "code", "source_file": "C:\\Users\\vitou\\laravel13.x\\examples\\basic-laravel-filamentphp\\vendor\\scrivo\\highlight.php\\Highlight\\Mode.php", "source_location": "L183"}], "edges": [{"source": "c_users_vitou_laravel13_x_examples_basic_laravel_filamentphp_vendor_scrivo_highlight_php_highlight_mode_php", "target": "mode_mode", "relation": "contains", "confidence": "EXTRACTED", "source_file": "C:\\Users\\vitou\\laravel13.x\\examples\\basic-laravel-filamentphp\\vendor\\scrivo\\highlight.php\\Highlight\\Mode.php", "source_location": "L80", "weight": 1.0}, {"source": "mode_mode", "target": "mode_mode_normalize", "relation": "method", "confidence": "EXTRACTED", "source_file": "C:\\Users\\vitou\\laravel13.x\\examples\\basic-laravel-filamentphp\\vendor\\scrivo\\highlight.php\\Highlight\\Mode.php", "source_location": "L93", "weight": 1.0}, {"source": "mode_mode", "target": "mode_mode_handledeprecations", "relation": "method", "confidence": "EXTRACTED", "source_file": "C:\\Users\\vitou\\laravel13.x\\examples\\basic-laravel-filamentphp\\vendor\\scrivo\\highlight.php\\Highlight\\Mode.php", "source_location": "L183", "weight": 1.0}], "raw_calls": [{"caller_nid": "mode_mode_normalize", "callee": "isset", "source_file": "C:\\Users\\vitou\\laravel13.x\\examples\\basic-laravel-filamentphp\\vendor\\scrivo\\highlight.php\\Highlight\\Mode.php", "source_location": "L96"}, {"caller_nid": "mode_mode_normalize", "callee": "isset", "source_file": "C:\\Users\\vitou\\laravel13.x\\examples\\basic-laravel-filamentphp\\vendor\\scrivo\\highlight.php\\Highlight\\Mode.php", "source_location": "L155"}, {"caller_nid": "mode_mode_normalize", "callee": "str_replace", "source_file": "C:\\Users\\vitou\\laravel13.x\\examples\\basic-laravel-filamentphp\\vendor\\scrivo\\highlight.php\\Highlight\\Mode.php", "source_location": "L156"}, {"caller_nid": "mode_mode_normalize", "callee": "str_replace", "source_file": "C:\\Users\\vitou\\laravel13.x\\examples\\basic-laravel-filamentphp\\vendor\\scrivo\\highlight.php\\Highlight\\Mode.php", "source_location": "L157"}, {"caller_nid": "mode_mode_normalize", "callee": "isset", "source_file": "C:\\Users\\vitou\\laravel13.x\\examples\\basic-laravel-filamentphp\\vendor\\scrivo\\highlight.php\\Highlight\\Mode.php", "source_location": "L162"}, {"caller_nid": "mode_mode_normalize", "callee": "is_object", "source_file": "C:\\Users\\vitou\\laravel13.x\\examples\\basic-laravel-filamentphp\\vendor\\scrivo\\highlight.php\\Highlight\\Mode.php", "source_location": "L162"}, {"caller_nid": "mode_mode_normalize", "callee": "is_object", "source_file": "C:\\Users\\vitou\\laravel13.x\\examples\\basic-laravel-filamentphp\\vendor\\scrivo\\highlight.php\\Highlight\\Mode.php", "source_location": "L168"}]}