{"nodes": [{"id": "c_users_vitou_laravel13_x_examples_basic_laravel_filamentphp_vendor_league_csv_src_callbackstreamfilter_php", "label": "CallbackStreamFilter.php", "file_type": "code", "source_file": "C:\\Users\\vitou\\laravel13.x\\examples\\basic-laravel-filamentphp\\vendor\\league\\csv\\src\\CallbackStreamFilter.php", "source_location": "L1"}, {"id": "callbackstreamfilter_callbackstreamfilter", "label": "CallbackStreamFilter", "file_type": "code", "source_file": "C:\\Users\\vitou\\laravel13.x\\examples\\basic-laravel-filamentphp\\vendor\\league\\csv\\src\\CallbackStreamFilter.php", "source_location": "L38"}, {"id": "callbackstreamfilter_callbackstreamfilter_oncreate", "label": ".onCreate()", "file_type": "code", "source_file": "C:\\Users\\vitou\\laravel13.x\\examples\\basic-laravel-filamentphp\\vendor\\league\\csv\\src\\CallbackStreamFilter.php", "source_location": "L46"}, {"id": "callbackstreamfilter_callbackstreamfilter_onclose", "label": ".onClose()", "file_type": "code", "source_file": "C:\\Users\\vitou\\laravel13.x\\examples\\basic-laravel-filamentphp\\vendor\\league\\csv\\src\\CallbackStreamFilter.php", "source_location": "L53"}, {"id": "callbackstreamfilter_callbackstreamfilter_filter", "label": ".filter()", "file_type": "code", "source_file": "C:\\Users\\vitou\\laravel13.x\\examples\\basic-laravel-filamentphp\\vendor\\league\\csv\\src\\CallbackStreamFilter.php", "source_location": "L58"}, {"id": "callbackstreamfilter_callbackstreamfilter_register", "label": ".register()", "file_type": "code", "source_file": "C:\\Users\\vitou\\laravel13.x\\examples\\basic-laravel-filamentphp\\vendor\\league\\csv\\src\\CallbackStreamFilter.php", "source_location": "L91"}, {"id": "callbackstreamfilter_callbackstreamfilter_normalizecallback", "label": ".normalizeCallback()", "file_type": "code", "source_file": "C:\\Users\\vitou\\laravel13.x\\examples\\basic-laravel-filamentphp\\vendor\\league\\csv\\src\\CallbackStreamFilter.php", "source_location": "L112"}, {"id": "callbackstreamfilter_callbackstreamfilter_isregistered", "label": ".isRegistered()", "file_type": "code", "source_file": "C:\\Users\\vitou\\laravel13.x\\examples\\basic-laravel-filamentphp\\vendor\\league\\csv\\src\\CallbackStreamFilter.php", "source_location": "L133"}, {"id": "callbackstreamfilter_callbackstreamfilter_registeredfilternames", "label": ".registeredFilternames()", "file_type": "code", "source_file": "C:\\Users\\vitou\\laravel13.x\\examples\\basic-laravel-filamentphp\\vendor\\league\\csv\\src\\CallbackStreamFilter.php", "source_location": "L143"}, {"id": "callbackstreamfilter_callbackstreamfilter_callback", "label": ".callback()", "file_type": "code", "source_file": "C:\\Users\\vitou\\laravel13.x\\examples\\basic-laravel-filamentphp\\vendor\\league\\csv\\src\\CallbackStreamFilter.php", "source_location": "L155"}], "edges": [{"source": "c_users_vitou_laravel13_x_examples_basic_laravel_filamentphp_vendor_league_csv_src_callbackstreamfilter_php", "target": "closure", "relation": "imports", "confidence": "EXTRACTED", "source_file": "C:\\Users\\vitou\\laravel13.x\\examples\\basic-laravel-filamentphp\\vendor\\league\\csv\\src\\CallbackStreamFilter.php", "source_location": "L16", "weight": 1.0}, {"source": "c_users_vitou_laravel13_x_examples_basic_laravel_filamentphp_vendor_league_csv_src_callbackstreamfilter_php", "target": "logicexception", "relation": "imports", "confidence": "EXTRACTED", "source_file": "C:\\Users\\vitou\\laravel13.x\\examples\\basic-laravel-filamentphp\\vendor\\league\\csv\\src\\CallbackStreamFilter.php", "source_location": "L17", "weight": 1.0}, {"source": "c_users_vitou_laravel13_x_examples_basic_laravel_filamentphp_vendor_league_csv_src_callbackstreamfilter_php", "target": "outofboundsexception", "relation": "imports", "confidence": "EXTRACTED", "source_file": "C:\\Users\\vitou\\laravel13.x\\examples\\basic-laravel-filamentphp\\vendor\\league\\csv\\src\\CallbackStreamFilter.php", "source_location": "L18", "weight": 1.0}, {"source": "c_users_vitou_laravel13_x_examples_basic_laravel_filamentphp_vendor_league_csv_src_callbackstreamfilter_php", "target": "php_user_filter", "relation": "imports", "confidence": "EXTRACTED", "source_file": "C:\\Users\\vitou\\laravel13.x\\examples\\basic-laravel-filamentphp\\vendor\\league\\csv\\src\\CallbackStreamFilter.php", "source_location": "L19", "weight": 1.0}, {"source": "c_users_vitou_laravel13_x_examples_basic_laravel_filamentphp_vendor_league_csv_src_callbackstreamfilter_php", "target": "reflectionexception", "relation": "imports", "confidence": "EXTRACTED", "source_file": "C:\\Users\\vitou\\laravel13.x\\examples\\basic-laravel-filamentphp\\vendor\\league\\csv\\src\\CallbackStreamFilter.php", "source_location": "L20", "weight": 1.0}, {"source": "c_users_vitou_laravel13_x_examples_basic_laravel_filamentphp_vendor_league_csv_src_callbackstreamfilter_php", "target": "reflectionfunction", "relation": "imports", "confidence": "EXTRACTED", "source_file": "C:\\Users\\vitou\\laravel13.x\\examples\\basic-laravel-filamentphp\\vendor\\league\\csv\\src\\CallbackStreamFilter.php", "source_location": "L21", "weight": 1.0}, {"source": "c_users_vitou_laravel13_x_examples_basic_laravel_filamentphp_vendor_league_csv_src_callbackstreamfilter_php", "target": "runtimeexception", "relation": "imports", "confidence": "EXTRACTED", "source_file": "C:\\Users\\vitou\\laravel13.x\\examples\\basic-laravel-filamentphp\\vendor\\league\\csv\\src\\CallbackStreamFilter.php", "source_location": "L22", "weight": 1.0}, {"source": "c_users_vitou_laravel13_x_examples_basic_laravel_filamentphp_vendor_league_csv_src_callbackstreamfilter_php", "target": "throwable", "relation": "imports", "confidence": "EXTRACTED", "source_file": "C:\\Users\\vitou\\laravel13.x\\examples\\basic-laravel-filamentphp\\vendor\\league\\csv\\src\\CallbackStreamFilter.php", "source_location": "L23", "weight": 1.0}, {"source": "c_users_vitou_laravel13_x_examples_basic_laravel_filamentphp_vendor_league_csv_src_callbackstreamfilter_php", "target": "valueerror", "relation": "imports", "confidence": "EXTRACTED", "source_file": "C:\\Users\\vitou\\laravel13.x\\examples\\basic-laravel-filamentphp\\vendor\\league\\csv\\src\\CallbackStreamFilter.php", "source_location": "L24", "weight": 1.0}, {"source": "c_users_vitou_laravel13_x_examples_basic_laravel_filamentphp_vendor_league_csv_src_callbackstreamfilter_php", "target": "array_keys", "relation": "imports", "confidence": "EXTRACTED", "source_file": "C:\\Users\\vitou\\laravel13.x\\examples\\basic-laravel-filamentphp\\vendor\\league\\csv\\src\\CallbackStreamFilter.php", "source_location": "L26", "weight": 1.0}, {"source": "c_users_vitou_laravel13_x_examples_basic_laravel_filamentphp_vendor_league_csv_src_callbackstreamfilter_php", "target": "in_array", "relation": "imports", "confidence": "EXTRACTED", "source_file": "C:\\Users\\vitou\\laravel13.x\\examples\\basic-laravel-filamentphp\\vendor\\league\\csv\\src\\CallbackStreamFilter.php", "source_location": "L27", "weight": 1.0}, {"source": "c_users_vitou_laravel13_x_examples_basic_laravel_filamentphp_vendor_league_csv_src_callbackstreamfilter_php", "target": "stream_bucket_append", "relation": "imports", "confidence": "EXTRACTED", "source_file": "C:\\Users\\vitou\\laravel13.x\\examples\\basic-laravel-filamentphp\\vendor\\league\\csv\\src\\CallbackStreamFilter.php", "source_location": "L28", "weight": 1.0}, {"source": "c_users_vitou_laravel13_x_examples_basic_laravel_filamentphp_vendor_league_csv_src_callbackstreamfilter_php", "target": "stream_bucket_make_writeable", "relation": "imports", "confidence": "EXTRACTED", "source_file": "C:\\Users\\vitou\\laravel13.x\\examples\\basic-laravel-filamentphp\\vendor\\league\\csv\\src\\CallbackStreamFilter.php", "source_location": "L29", "weight": 1.0}, {"source": "c_users_vitou_laravel13_x_examples_basic_laravel_filamentphp_vendor_league_csv_src_callbackstreamfilter_php", "target": "stream_bucket_new", "relation": "imports", "confidence": "EXTRACTED", "source_file": "C:\\Users\\vitou\\laravel13.x\\examples\\basic-laravel-filamentphp\\vendor\\league\\csv\\src\\CallbackStreamFilter.php", "source_location": "L30", "weight": 1.0}, {"source": "c_users_vitou_laravel13_x_examples_basic_laravel_filamentphp_vendor_league_csv_src_callbackstreamfilter_php", "target": "stream_filter_register", "relation": "imports", "confidence": "EXTRACTED", "source_file": "C:\\Users\\vitou\\laravel13.x\\examples\\basic-laravel-filamentphp\\vendor\\league\\csv\\src\\CallbackStreamFilter.php", "source_location": "L31", "weight": 1.0}, {"source": "c_users_vitou_laravel13_x_examples_basic_laravel_filamentphp_vendor_league_csv_src_callbackstreamfilter_php", "target": "stream_get_filters", "relation": "imports", "confidence": "EXTRACTED", "source_file": "C:\\Users\\vitou\\laravel13.x\\examples\\basic-laravel-filamentphp\\vendor\\league\\csv\\src\\CallbackStreamFilter.php", "source_location": "L32", "weight": 1.0}, {"source": "c_users_vitou_laravel13_x_examples_basic_laravel_filamentphp_vendor_league_csv_src_callbackstreamfilter_php", "target": "psfs_err_fatal", "relation": "imports", "confidence": "EXTRACTED", "source_file": "C:\\Users\\vitou\\laravel13.x\\examples\\basic-laravel-filamentphp\\vendor\\league\\csv\\src\\CallbackStreamFilter.php", "source_location": "L34", "weight": 1.0}, {"source": "c_users_vitou_laravel13_x_examples_basic_laravel_filamentphp_vendor_league_csv_src_callbackstreamfilter_php", "target": "psfs_feed_me", "relation": "imports", "confidence": "EXTRACTED", "source_file": "C:\\Users\\vitou\\laravel13.x\\examples\\basic-laravel-filamentphp\\vendor\\league\\csv\\src\\CallbackStreamFilter.php", "source_location": "L35", "weight": 1.0}, {"source": "c_users_vitou_laravel13_x_examples_basic_laravel_filamentphp_vendor_league_csv_src_callbackstreamfilter_php", "target": "psfs_pass_on", "relation": "imports", "confidence": "EXTRACTED", "source_file": "C:\\Users\\vitou\\laravel13.x\\examples\\basic-laravel-filamentphp\\vendor\\league\\csv\\src\\CallbackStreamFilter.php", "source_location": "L36", "weight": 1.0}, {"source": "c_users_vitou_laravel13_x_examples_basic_laravel_filamentphp_vendor_league_csv_src_callbackstreamfilter_php", "target": "callbackstreamfilter_callbackstreamfilter", "relation": "contains", "confidence": "EXTRACTED", "source_file": "C:\\Users\\vitou\\laravel13.x\\examples\\basic-laravel-filamentphp\\vendor\\league\\csv\\src\\CallbackStreamFilter.php", "source_location": "L38", "weight": 1.0}, {"source": "callbackstreamfilter_callbackstreamfilter", "target": "callbackstreamfilter_callbackstreamfilter_oncreate", "relation": "method", "confidence": "EXTRACTED", "source_file": "C:\\Users\\vitou\\laravel13.x\\examples\\basic-laravel-filamentphp\\vendor\\league\\csv\\src\\CallbackStreamFilter.php", "source_location": "L46", "weight": 1.0}, {"source": "callbackstreamfilter_callbackstreamfilter", "target": "callbackstreamfilter_callbackstreamfilter_onclose", "relation": "method", "confidence": "EXTRACTED", "source_file": "C:\\Users\\vitou\\laravel13.x\\examples\\basic-laravel-filamentphp\\vendor\\league\\csv\\src\\CallbackStreamFilter.php", "source_location": "L53", "weight": 1.0}, {"source": "callbackstreamfilter_callbackstreamfilter", "target": "callbackstreamfilter_callbackstreamfilter_filter", "relation": "method", "confidence": "EXTRACTED", "source_file": "C:\\Users\\vitou\\laravel13.x\\examples\\basic-laravel-filamentphp\\vendor\\league\\csv\\src\\CallbackStreamFilter.php", "source_location": "L58", "weight": 1.0}, {"source": "callbackstreamfilter_callbackstreamfilter", "target": "callbackstreamfilter_callbackstreamfilter_register", "relation": "method", "confidence": "EXTRACTED", "source_file": "C:\\Users\\vitou\\laravel13.x\\examples\\basic-laravel-filamentphp\\vendor\\league\\csv\\src\\CallbackStreamFilter.php", "source_location": "L91", "weight": 1.0}, {"source": "callbackstreamfilter_callbackstreamfilter", "target": "callbackstreamfilter_callbackstreamfilter_normalizecallback", "relation": "method", "confidence": "EXTRACTED", "source_file": "C:\\Users\\vitou\\laravel13.x\\examples\\basic-laravel-filamentphp\\vendor\\league\\csv\\src\\CallbackStreamFilter.php", "source_location": "L112", "weight": 1.0}, {"source": "callbackstreamfilter_callbackstreamfilter", "target": "callbackstreamfilter_callbackstreamfilter_isregistered", "relation": "method", "confidence": "EXTRACTED", "source_file": "C:\\Users\\vitou\\laravel13.x\\examples\\basic-laravel-filamentphp\\vendor\\league\\csv\\src\\CallbackStreamFilter.php", "source_location": "L133", "weight": 1.0}, {"source": "callbackstreamfilter_callbackstreamfilter", "target": "callbackstreamfilter_callbackstreamfilter_registeredfilternames", "relation": "method", "confidence": "EXTRACTED", "source_file": "C:\\Users\\vitou\\laravel13.x\\examples\\basic-laravel-filamentphp\\vendor\\league\\csv\\src\\CallbackStreamFilter.php", "source_location": "L143", "weight": 1.0}, {"source": "callbackstreamfilter_callbackstreamfilter", "target": "callbackstreamfilter_callbackstreamfilter_callback", "relation": "method", "confidence": "EXTRACTED", "source_file": "C:\\Users\\vitou\\laravel13.x\\examples\\basic-laravel-filamentphp\\vendor\\league\\csv\\src\\CallbackStreamFilter.php", "source_location": "L155", "weight": 1.0}, {"source": "callbackstreamfilter_callbackstreamfilter_filter", "target": "callbackstreamfilter_callbackstreamfilter_onclose", "relation": "calls", "confidence": "EXTRACTED", "source_file": "C:\\Users\\vitou\\laravel13.x\\examples\\basic-laravel-filamentphp\\vendor\\league\\csv\\src\\CallbackStreamFilter.php", "source_location": "L73", "weight": 1.0}], "raw_calls": [{"caller_nid": "callbackstreamfilter_callbackstreamfilter_filter", "callee": "stream_bucket_make_writeable", "source_file": "C:\\Users\\vitou\\laravel13.x\\examples\\basic-laravel-filamentphp\\vendor\\league\\csv\\src\\CallbackStreamFilter.php", "source_location": "L61"}, {"caller_nid": "callbackstreamfilter_callbackstreamfilter_filter", "callee": "($this->callback)", "source_file": "C:\\Users\\vitou\\laravel13.x\\examples\\basic-laravel-filamentphp\\vendor\\league\\csv\\src\\CallbackStreamFilter.php", "source_location": "L71"}, {"caller_nid": "callbackstreamfilter_callbackstreamfilter_filter", "callee": "trigger_error", "source_file": "C:\\Users\\vitou\\laravel13.x\\examples\\basic-laravel-filamentphp\\vendor\\league\\csv\\src\\CallbackStreamFilter.php", "source_location": "L74"}, {"caller_nid": "callbackstreamfilter_callbackstreamfilter_filter", "callee": "getMessage", "source_file": "C:\\Users\\vitou\\laravel13.x\\examples\\basic-laravel-filamentphp\\vendor\\league\\csv\\src\\CallbackStreamFilter.php", "source_location": "L74"}, {"caller_nid": "callbackstreamfilter_callbackstreamfilter_filter", "callee": "Warning", "source_file": "C:\\Users\\vitou\\laravel13.x\\examples\\basic-laravel-filamentphp\\vendor\\league\\csv\\src\\CallbackStreamFilter.php", "source_location": "L79"}, {"caller_nid": "callbackstreamfilter_callbackstreamfilter_filter", "callee": "stream_bucket_append", "source_file": "C:\\Users\\vitou\\laravel13.x\\examples\\basic-laravel-filamentphp\\vendor\\league\\csv\\src\\CallbackStreamFilter.php", "source_location": "L80"}, {"caller_nid": "callbackstreamfilter_callbackstreamfilter_filter", "callee": "stream_bucket_new", "source_file": "C:\\Users\\vitou\\laravel13.x\\examples\\basic-laravel-filamentphp\\vendor\\league\\csv\\src\\CallbackStreamFilter.php", "source_location": "L80"}, {"caller_nid": "callbackstreamfilter_callbackstreamfilter_register", "callee": "isset", "source_file": "C:\\Users\\vitou\\laravel13.x\\examples\\basic-laravel-filamentphp\\vendor\\league\\csv\\src\\CallbackStreamFilter.php", "source_location": "L93"}, {"caller_nid": "callbackstreamfilter_callbackstreamfilter_register", "callee": "in_array", "source_file": "C:\\Users\\vitou\\laravel13.x\\examples\\basic-laravel-filamentphp\\vendor\\league\\csv\\src\\CallbackStreamFilter.php", "source_location": "L93"}, {"caller_nid": "callbackstreamfilter_callbackstreamfilter_register", "callee": "stream_get_filters", "source_file": "C:\\Users\\vitou\\laravel13.x\\examples\\basic-laravel-filamentphp\\vendor\\league\\csv\\src\\CallbackStreamFilter.php", "source_location": "L93"}, {"caller_nid": "callbackstreamfilter_callbackstreamfilter_register", "callee": "self", "source_file": "C:\\Users\\vitou\\laravel13.x\\examples\\basic-laravel-filamentphp\\vendor\\league\\csv\\src\\CallbackStreamFilter.php", "source_location": "L97"}, {"caller_nid": "callbackstreamfilter_callbackstreamfilter_register", "callee": "stream_filter_register", "source_file": "C:\\Users\\vitou\\laravel13.x\\examples\\basic-laravel-filamentphp\\vendor\\league\\csv\\src\\CallbackStreamFilter.php", "source_location": "L98"}, {"caller_nid": "callbackstreamfilter_callbackstreamfilter_normalizecallback", "callee": "$callback", "source_file": "C:\\Users\\vitou\\laravel13.x\\examples\\basic-laravel-filamentphp\\vendor\\league\\csv\\src\\CallbackStreamFilter.php", "source_location": "L115"}, {"caller_nid": "callbackstreamfilter_callbackstreamfilter_normalizecallback", "callee": "isInternal", "source_file": "C:\\Users\\vitou\\laravel13.x\\examples\\basic-laravel-filamentphp\\vendor\\league\\csv\\src\\CallbackStreamFilter.php", "source_location": "L119"}, {"caller_nid": "callbackstreamfilter_callbackstreamfilter_normalizecallback", "callee": "getNumberOfParameters", "source_file": "C:\\Users\\vitou\\laravel13.x\\examples\\basic-laravel-filamentphp\\vendor\\league\\csv\\src\\CallbackStreamFilter.php", "source_location": "L123"}, {"caller_nid": "callbackstreamfilter_callbackstreamfilter_normalizecallback", "callee": "getName", "source_file": "C:\\Users\\vitou\\laravel13.x\\examples\\basic-laravel-filamentphp\\vendor\\league\\csv\\src\\CallbackStreamFilter.php", "source_location": "L124"}, {"caller_nid": "callbackstreamfilter_callbackstreamfilter_normalizecallback", "callee": "$callback", "source_file": "C:\\Users\\vitou\\laravel13.x\\examples\\basic-laravel-filamentphp\\vendor\\league\\csv\\src\\CallbackStreamFilter.php", "source_location": "L127"}, {"caller_nid": "callbackstreamfilter_callbackstreamfilter_isregistered", "callee": "isset", "source_file": "C:\\Users\\vitou\\laravel13.x\\examples\\basic-laravel-filamentphp\\vendor\\league\\csv\\src\\CallbackStreamFilter.php", "source_location": "L135"}, {"caller_nid": "callbackstreamfilter_callbackstreamfilter_registeredfilternames", "callee": "array_keys", "source_file": "C:\\Users\\vitou\\laravel13.x\\examples\\basic-laravel-filamentphp\\vendor\\league\\csv\\src\\CallbackStreamFilter.php", "source_location": "L145"}]}