{
  "id": "95a3b3e1",
  "phase": "agent_error",
  "pageUrl": "/admin/users",
  "sourceFile": null,
  "previewFile": null,
  "previewMode": null,
  "expectedVariants": 3,
  "arrivedVariants": 0,
  "visibleVariant": 0,
  "paramValues": {},
  "pendingEventSeq": null,
  "pendingEvent": null,
  "deliveryLease": null,
  "checkpointRevision": 1,
  "activeOwner": "a1f95816",
  "sourceMarkers": {},
  "fallbackMode": null,
  "annotationArtifacts": [],
  "diagnostics": [
    {
      "error": "agent_error",
      "message": "Reset: no agent poll loop was running. Start live mode in Cursor and keep polling."
    }
  ],
  "updatedAt": "2026-06-06T12:52:37.671Z"
}
